{
  "ticker": "MSFT",
  "company_id": "b1a30119-ae6f-4362-a829-1b56362194ba",
  "signal_id": "478a3a24-cb36-462f-9f55-78186d088bce",
  "collected_at": "2026-03-22T18:18:57.780811",
  "summary": {
    "culture_score": 50.0,
    "innovation_score": 50.0,
    "data_driven_score": 50.0,
    "change_readiness_score": 50.0,
    "ai_awareness_score": 50.0,
    "review_count": 0,
    "avg_rating": 3.0,
    "confidence": 0.1,
    "current_employee_ratio": 0.5,
    "rationale": "Mixed employee sentiment; moderate innovation; emerging data culture; 0 reviews"
  },
  "reviews": [],
  "positive_keywords": [],
  "negative_keywords": []
}